[
  {
    "full_name": "atom/atom",
    "stargazers_count": 53853,
    "open_issues_count": 736,
    "forks_count": 15514
  },
  {
    "full_name": "open-sauced/open-sauced",
    "stargazers_count": 316,
    "open_issues_count": 29,
    "forks_count": 90
  },
  {
    "full_name": "expressjs/express",
    "stargazers_count": 51242,
    "open_issues_count": 155,
    "forks_count": 8559
  },
  {
    "full_name": "Kilian/fromscratch",
    "stargazers_count": 596,
    "open_issues_count": 38,
    "forks_count": 61
  },
  {
    "full_name": "Automattic/simplenote-electron",
    "stargazers_count": 3288,
    "open_issues_count": 123,
    "forks_count": 465
  },
  {
    "full_name": "t9md/atom-vim-mode-plus",
    "stargazers_count": 1387,
    "open_issues_count": 121,
    "forks_count": 113
  }
]